growmax/__init__.py
growmax/config.py
growmax/constants.py
growmax/moisture.py
growmax/ntpclient.py
growmax/pump.py
growmax/routine.py
growmax/atlas_ph/__init__.py
growmax/atlas_ph/calibration.py
growmax/atlas_ph/export.py
growmax/atlas_ph/i2c.py
growmax/atlas_ph/import_config.py
growmax/atlas_ph/set_i2c.py
growmax/atlas_ph/uart_read.py
growmax/displays/__init__.py
growmax/displays/sh1107.py
growmax/displays/ssd1327.py
growmax/relays/__init__.py
growmax/relays/i2c_relays.py
growmax/sensors/__init__.py
growmax/sensors/adafruit_scd4x.py
growmax/sensors/motion.py
growmax/utils/__init__.py
growmax/utils/api.py
growmax/utils/configs.py
growmax/utils/displays.py
growmax/utils/mcu.py
growmax/utils/relays.py
growmax/utils/sensors.py
growmax/utils/water.py
growmax/utils/wifi.py
growmax-1.2.7.dist-info/LICENSE
growmax-1.2.7.dist-info/METADATA
growmax-1.2.7.dist-info/WHEEL
growmax-1.2.7.dist-info/top_level.txt
growmax-1.2.7.dist-info/RECORD
