Metadata-Version: 2.1
Name: growmax
Version: 1.2.7
Summary: Micropython routines for automated plant watering and monitoring.
Author-email: "Matt Davis and OpenSensor.io" <matteius@gmail.com>
License: BSD 3-Clause License
Project-URL: Homepage, https://www.opensensor.io
Project-URL: Repository, https://github.com/opensensor/growmax.git
Project-URL: Issues, https://github.com/opensensor/growmax/issues
Classifier: Programming Language :: Python :: Implementation :: MicroPython
Classifier: License :: OSI Approved :: MIT License
Classifier: Operating System :: OS Independent
Requires-Python: >=3.8
License-File: LICENSE
